config_reader/Config.py
config_reader/__init__.py
tests/__init__.py
config_reader_ryazantseff-0.0.1.dist-info/LICENSE
config_reader_ryazantseff-0.0.1.dist-info/METADATA
config_reader_ryazantseff-0.0.1.dist-info/WHEEL
config_reader_ryazantseff-0.0.1.dist-info/top_level.txt
config_reader_ryazantseff-0.0.1.dist-info/RECORD
